flightless_pylint_plugin/__init__.py
flightless_pylint_plugin/no_conditionals_in_test.py
flightless_pylint_plugin/no_direct_settings_import.py
flightless_pylint_plugin/no_pytest_skip.py
flightless_pylint_plugin-0.3.0.dist-info/LICENSE
flightless_pylint_plugin-0.3.0.dist-info/METADATA
flightless_pylint_plugin-0.3.0.dist-info/WHEEL
flightless_pylint_plugin-0.3.0.dist-info/RECORD
